dhuolib/__init__.py
dhuolib/auth.py
dhuolib/config.py
dhuolib/messages.py
dhuolib/repository.py
dhuolib/services.py
dhuolib/utils.py
dhuolib/validations.py
dhuolib/__pycache__/__init__.cpython-311.pyc
dhuolib/__pycache__/__init__.cpython-39.pyc
dhuolib/__pycache__/clients.cpython-311.pyc
dhuolib/__pycache__/clients.cpython-39.pyc
dhuolib/__pycache__/config.cpython-311.pyc
dhuolib/__pycache__/repository.cpython-311.pyc
dhuolib/__pycache__/services.cpython-311.pyc
dhuolib/__pycache__/utils.cpython-311.pyc
dhuolib/__pycache__/validations.cpython-311.pyc
dhuolib/clients/__init__.py
dhuolib/clients/experiment.py
dhuolib/clients/platform.py
dhuolib/clients/__pycache__/__init__.cpython-311.pyc
dhuolib/clients/__pycache__/experiment.cpython-311.pyc
dhuolib/clients/__pycache__/platform.cpython-311.pyc
dhuodata_lib-0.7.8.dist-info/METADATA
dhuodata_lib-0.7.8.dist-info/WHEEL
dhuodata_lib-0.7.8.dist-info/top_level.txt
dhuodata_lib-0.7.8.dist-info/RECORD
